newtopythonpypi/__init__.py
newtopythonpypi/newtopythonpypi.py
newtopythonpypi-1.0.dist-info/METADATA
newtopythonpypi-1.0.dist-info/WHEEL
newtopythonpypi-1.0.dist-info/top_level.txt
newtopythonpypi-1.0.dist-info/RECORD
