Metadata-Version: 2.1
Name: newtopythonpypi
Version: 1.0
Summary: Python newbi
Home-page: http://github.com/sourabhjains
Author: Sourabh Jain
Author-email: jainsourabh679@gmail.com
License: MIT
Platform: UNKNOWN
